deluca/core.py
deluca/version.py
deluca/agents/__init__.py
deluca/agents/_adaptive.py
deluca/agents/_bang_bang.py
deluca/agents/_bpc.py
deluca/agents/_deep.py
deluca/agents/_drc.py
deluca/agents/_gpc.py
deluca/agents/_hinf.py
deluca/agents/_igpc.py
deluca/agents/_ilc.py
deluca/agents/_ilqr.py
deluca/agents/_lqr.py
deluca/agents/_pid.py
deluca/agents/_random.py
deluca/agents/_zero.py
deluca/agents/core.py
deluca/envs/__init__.py
deluca/envs/_brax.py
deluca/envs/_lds.py
deluca/envs/classic/_acrobot.py
deluca/envs/classic/_cartpole.py
deluca/envs/classic/_mountain_car.py
deluca/envs/classic/_pendulum.py
deluca/envs/classic/_planar_quadrotor.py
deluca/envs/classic/_reacher.py
deluca/envs/lung/__init__.py
deluca/envs/lung/_balloon_lung.py
deluca/envs/lung/_delay_lung.py
deluca/envs/lung/_learned_lung.py
deluca/envs/lung/core.py
deluca/utils/__init__.py
deluca/utils/experiment.py
deluca/utils/planning.py
plugin/setup.py
scripts/make_plugin.py
deluca-0.0.17.dist-info/LICENSE
deluca-0.0.17.dist-info/METADATA
deluca-0.0.17.dist-info/WHEEL
deluca-0.0.17.dist-info/top_level.txt
deluca-0.0.17.dist-info/RECORD
