Metadata-Version: 2.1
Name: deluca
Version: 0.0.17
Summary: UNKNOWN
Home-page: https://github.com/google/deluca
Author: Google AI Princeton
Author-email: dsuo@google.com
License: Apache License
Keywords: differentiable,control algorithms,reinforcement learning
Platform: UNKNOWN
Classifier: Programming Language :: Python :: 3
Classifier: License :: OSI Approved :: Apache Software License
Classifier: Operating System :: OS Independent
Classifier: Development Status :: 3 - Alpha
Requires-Python: >=3.7
Requires-Dist: numpy
Requires-Dist: scipy
Requires-Dist: jax
Requires-Dist: optax
Requires-Dist: flax
Requires-Dist: brax
Provides-Extra: dev
Requires-Dist: pathos ; extra == 'dev'
Requires-Dist: tqdm ; extra == 'dev'
Requires-Dist: jupyter ; extra == 'dev'
Requires-Dist: ipython ; extra == 'dev'
Requires-Dist: pytest ; extra == 'dev'
Requires-Dist: flake8 ; extra == 'dev'
Requires-Dist: flake8-print ; extra == 'dev'
Requires-Dist: flake8-bugbear ; extra == 'dev'
Requires-Dist: mypy ; extra == 'dev'
Requires-Dist: pytest-cov ; extra == 'dev'
Requires-Dist: pytest-instafail ; extra == 'dev'
Requires-Dist: pytest-xdist ; extra == 'dev'
Requires-Dist: pylint ; extra == 'dev'
Requires-Dist: black ; extra == 'dev'
Requires-Dist: reorder-python-imports ; extra == 'dev'
Requires-Dist: autoflake ; extra == 'dev'
Requires-Dist: pre-commit ; extra == 'dev'
Requires-Dist: pydocstring-coverage ; extra == 'dev'
Requires-Dist: bumpversion ; extra == 'dev'
Requires-Dist: gprof2dot ; extra == 'dev'
Requires-Dist: bandit ; extra == 'dev'
Requires-Dist: check-python-versions ; extra == 'dev'
Requires-Dist: line-profiler ; extra == 'dev'
Provides-Extra: docs
Requires-Dist: sphinx ; extra == 'docs'
Requires-Dist: sphinxcontrib-napoleon ; extra == 'docs'
Requires-Dist: sphinx-rtd-theme ; extra == 'docs'
